adafruit_trellism4.py
adafruit_circuitpython_trellism4-1.5.23.dist-info/licenses/LICENSE
adafruit_circuitpython_trellism4-1.5.23.dist-info/METADATA
adafruit_circuitpython_trellism4-1.5.23.dist-info/WHEEL
adafruit_circuitpython_trellism4-1.5.23.dist-info/top_level.txt
adafruit_circuitpython_trellism4-1.5.23.dist-info/RECORD
