Metadata-Version: 2.4
Name: adafruit-circuitpython-trellism4
Version: 1.5.23
Summary: CircuitPython library Trellis M4 Express.
Author-email: Adafruit Industries <circuitpython@adafruit.com>
License: MIT
Project-URL: Homepage, https://github.com/adafruit/Adafruit_CircuitPython_TrellisM4
Keywords: adafruit,trellism4,hardware,micropython,circuitpython
Classifier: Intended Audience :: Developers
Classifier: Topic :: Software Development :: Libraries
Classifier: Topic :: Software Development :: Embedded Systems
Classifier: Topic :: System :: Hardware
Classifier: License :: OSI Approved :: MIT License
Classifier: Programming Language :: Python :: 3
License-File: LICENSE
Requires-Dist: Adafruit-Blinka
Requires-Dist: adafruit-circuitpython-matrixkeypad
Requires-Dist: adafruit-circuitpython-neopixel
Requires-Dist: typing-extensions~=4.0
Provides-Extra: optional
Dynamic: license-file
